datasynth/__init__.py
datasynth/cli/__init__.py
datasynth/cli/commands/__init__.py
datasynth/cli/commands/example_cmd.py
datasynth/models/__init__.py
datasynth/models/person.py
tests/__init__.py
tests/test_person.py
datasynth-0.0.5.dist-info/METADATA
datasynth-0.0.5.dist-info/WHEEL
datasynth-0.0.5.dist-info/entry_points.txt
datasynth-0.0.5.dist-info/top_level.txt
datasynth-0.0.5.dist-info/RECORD
