Metadata-Version: 2.1
Name: datasynth
Version: 0.0.5
Summary: Synthetic data for your app.
Home-page: http://github.com/New-Math-Data/datasynth
Author: Traey Hatch
Author-email: thatch@newmathdata.com
License: http://github.com/New-Math-Data/datasynth
Project-URL: Source, https://github.com/New-Math-Data/datasynth
Platform: UNKNOWN
Classifier: Development Status :: 5 - Production/Stable
Classifier: Intended Audience :: Developers
Classifier: Natural Language :: English
Classifier: License :: OSI Approved :: Apache Software License
Classifier: Programming Language :: Python
Classifier: Programming Language :: Python :: 3.8
Classifier: Programming Language :: Python :: 3.9
Classifier: Programming Language :: Python :: Implementation :: CPython
Classifier: Programming Language :: Python :: Implementation :: PyPy
Requires-Python: >=3.8
Requires-Dist: click (==8.1.3)
Requires-Dist: faker (==13.11.1)
Requires-Dist: gytrash (==0.0.21)
Requires-Dist: requests (==2.27.1)
Requires-Dist: pandas (==1.4.2)
Provides-Extra: dev
Requires-Dist: pre-commit (==2.13.0) ; extra == 'dev'
Requires-Dist: sphinx (==4.0.2) ; extra == 'dev'
Requires-Dist: sphinx-material (==0.0.32) ; extra == 'dev'
Requires-Dist: bump2version (==1.0.1) ; extra == 'dev'
Provides-Extra: test
Requires-Dist: flake8 (==4.0.1) ; extra == 'test'
Requires-Dist: pytest (==7.1.2) ; extra == 'test'
Requires-Dist: pytest-cov (==3.0.0) ; extra == 'test'
